{"stops":[{"name":"V Chotejně","lines":["111","329"],"platforms":[{"latitude":50057445,"longitude":14532622,"transport":"Bus","lines":["111","329"]},{"latitude":50058475,"longitude":14534358,"transport":"Bus","lines":["111","329"]}]},{"name":"V Korytech","lines":["101","188"],"platforms":[{"latitude":50054450,"longitude":14488595,"transport":"Bus","lines":["101","188"]},{"latitude":50054489,"longitude":14488890,"transport":"Bus","lines":["101","188"]}]},{"name":"V Ladech","lines":["165","326","327","385"],"platforms":[{"latitude":50013366,"longitude":14513722,"transport":"Bus","lines":["165","326","327","385"]},{"latitude":50013103,"longitude":14513911,"transport":"Bus","lines":["165","326","327","385"]}]},{"name":"V Lískách","lines":["193","293"],"platforms":[{"latitude":50019493,"longitude":14464202,"transport":"Bus","lines":["193","293","I1"]}]},{"name":"V Mokřinách","lines":["121"],"platforms":[{"latitude":50020168,"longitude":14407744,"transport":"Bus","lines":["121"]},{"latitude":50020156,"longitude":14407478,"transport":"Bus","lines":["121"]}]},{"name":"V Násypu","lines":["128","558"],"platforms":[{"latitude":50044704,"longitude":14402304,"transport":"Bus","lines":["128"]}]},{"name":"V Nových domcích","lines":["111","329"],"platforms":[{"latitude":50056560,"longitude":14533609,"transport":"Bus","lines":["111","329"]},{"latitude":50056453,"longitude":14534191,"transport":"Bus","lines":["111","329"]}]},{"name":"V Podbabě","lines":["107","116","147","160","340","350","355","359","502","604","615","P2"],"platforms":[{"latitude":50121406,"longitude":14393530,"transport":"Bus","lines":["107","116","147","160","340","350","355","359","502","604"]},{"latitude":50121238,"longitude":14393628,"transport":"Bus","lines":["107","116","147","160","340","350","355","359","502","604"]}]},{"name":"V Přístavu","lines":["156"],"platforms":[]},{"name":"V Remízku","lines":["230","246","247","248","601"],"platforms":[{"latitude":50026008,"longitude":14368698,"transport":"Bus","lines":["230","246","247","248","601"]}]},{"name":"V Rybníčkách","lines":["175"],"platforms":[{"latitude":50070587,"longitude":14506995,"transport":"Bus","lines":["175"]},{"latitude":50070590,"longitude":14507536,"transport":"Bus","lines":["175"]}]},{"name":"V Sedlci","lines":["107","147","502"],"platforms":[{"latitude":50128345,"longitude":14395261,"transport":"Bus","lines":["107","147","359","502"]},{"latitude":50128208,"longitude":14395142,"transport":"Bus","lines":["107","147","359","502"]}]},{"name":"V Sudech","lines":["165","246","256","601"],"platforms":[{"latitude":49992504,"longitude":14345608,"transport":"Bus","lines":["165","246","256","601"]},{"latitude":49992080,"longitude":14346195,"transport":"Bus","lines":["165","246","256","601"]}]},{"name":"V Uličce","lines":["104","120","558"],"platforms":[{"latitude":50041519,"longitude":14395602,"transport":"Bus","lines":["104","120"]}]},{"name":"V Zápolí","lines":["118","121","170","203","505"],"platforms":[{"latitude":50046123,"longitude":14468051,"transport":"Bus","lines":["118","121","170","203","505"]},{"latitude":50046047,"longitude":14467750,"transport":"Bus","lines":["170","203"]},{"latitude":50047843,"longitude":14468664,"transport":"Bus","lines":["118","121","505"]}]},{"name":"V Zátiší","lines":["121","563"],"platforms":[{"latitude":50022617,"longitude":14431615,"transport":"Bus","lines":["121"]},{"latitude":50022548,"longitude":14433133,"transport":"Bus","lines":["121"]}]},{"name":"Vackov","lines":["124","297","567"],"platforms":[{"latitude":50086837,"longitude":14486620,"transport":"Bus","lines":["124","297"]},{"latitude":50086906,"longitude":14487410,"transport":"Bus","lines":["124","297"]}]},{"name":"Vackova","lines":["214","225"],"platforms":[{"latitude":50045143,"longitude":14315393,"transport":"Bus","lines":["225"]},{"latitude":50044486,"longitude":14315313,"transport":"Bus","lines":["225"]}]},{"name":"Václavka","lines":["137","501"],"platforms":[{"latitude":50065269,"longitude":14393799,"transport":"Bus","lines":["137","501"]},{"latitude":50065223,"longitude":14393098,"transport":"Bus","lines":["137","501"]}]},{"name":"Václavské náměstí","lines":["3","9","14","24","51","52","54","55","56","58","91"],"platforms":[{"latitude":50081825,"longitude":14425451,"transport":"Tram","lines":["3","9","14","24","51","52","54","55","56","58"]},{"latitude":50082019,"longitude":14425831,"transport":"Tram","lines":["3","9","14","24","51","52","54","55","56","58"]}]},{"name":"Vajgarská","lines":["110","181","223","296"],"platforms":[{"latitude":50102157,"longitude":14554643,"transport":"Bus","lines":["110","181","223","296"]},{"latitude":50101913,"longitude":14554649,"transport":"Bus","lines":["110","181","223","296"]}]},{"name":"Valtická","lines":["257","306","607"],"platforms":[{"latitude":50066448,"longitude":14265938,"transport":"Bus","lines":["257","306","607"]},{"latitude":50065963,"longitude":14266409,"transport":"Bus","lines":["257","306","607"]}]},{"name":"Vápenka","lines":["1","9","16","58"],"platforms":[{"latitude":50091716,"longitude":14475474,"transport":"Tram","lines":["1","9","16","58"]},{"latitude":50091491,"longitude":14474866,"transport":"Tram","lines":["1","9","16","58"]}]},{"name":"Vavřenova","lines":["170","203"],"platforms":[{"latitude":50022628,"longitude":14426506,"transport":"Bus","lines":["170","203"]},{"latitude":50022789,"longitude":14425681,"transport":"Bus","lines":["170","203"]}]},{"name":"Ve Studeném","lines":["196","197","198","501"],"platforms":[{"latitude":50031566,"longitude":14421445,"transport":"Bus","lines":["196","197","198","501"]},{"latitude":50031566,"longitude":14423419,"transport":"Bus","lines":["196","197","198","501"]}]},{"name":"Ve Vilkách","lines":["363","605"],"platforms":[{"latitude":50015563,"longitude":14539332,"transport":"Bus","lines":["363","605"]}]},{"name":"Ve Výrech","lines":["249"],"platforms":[{"latitude":50034751,"longitude":14307274,"transport":"Bus","lines":["249"]},{"latitude":50034824,"longitude":14306717,"transport":"Bus","lines":["249"]}]},{"name":"Ve Žlíbku","lines":["269","273","512","562"],"platforms":[{"latitude":50110996,"longitude":14624568,"transport":"Bus","lines":["269","273","512"]},{"latitude":50110511,"longitude":14624604,"transport":"Bus","lines":["269"]},{"latitude":50110622,"longitude":14624840,"transport":"Bus","lines":["269"]},{"latitude":50111190,"longitude":14624424,"transport":"Bus","lines":["269","273","512"]}]},{"name":"Veletržní","lines":["12","14","15","17","53","54","91"],"platforms":[{"latitude":50101642,"longitude":14433060,"transport":"Tram","lines":["12","14","15","17","53","54"]},{"latitude":50102554,"longitude":14432750,"transport":"Tram","lines":["12","14","15","17","53","54"]}]},{"name":"Velká Chuchle","lines":["244"],"platforms":[{"latitude":50012161,"longitude":14380627,"transport":"Bus","lines":["172"]}]},{"name":"Velká Ohrada","lines":["174","235","508"],"platforms":[{"latitude":50035594,"longitude":14336010,"transport":"Bus","lines":["174","211","235","508"]},{"latitude":50035354,"longitude":14335907,"transport":"Bus","lines":["174","211","508"]}]},{"name":"Venušina","lines":["267"],"platforms":[{"latitude":50026943,"longitude":14608466,"transport":"Bus","lines":["267"]},{"latitude":50026042,"longitude":14608713,"transport":"Bus","lines":["267"]}]},{"name":"Veronské náměstí","lines":["183","240","271","511","570"],"platforms":[]},{"name":"Veslařský ostrov","lines":["P3"],"platforms":[]},{"name":"Větrník","lines":["1","2","18","56","179","191","510","560"],"platforms":[{"latitude":50089229,"longitude":14349222,"transport":"Bus","lines":["179","184","191","510"]},{"latitude":50089298,"longitude":14349083,"transport":"Bus","lines":["179","184","191","510"]},{"latitude":50089691,"longitude":14351069,"transport":"Tram","lines":["1","2","18","56"]},{"latitude":50090076,"longitude":14351989,"transport":"Tram","lines":["1","2","18","56"]}]},{"name":"Větrov","lines":["291"],"platforms":[{"latitude":50073604,"longitude":14424433,"transport":"Bus","lines":["291"]},{"latitude":50073440,"longitude":14424447,"transport":"Bus","lines":["291"]}]},{"name":"Vidoule","lines":["130","149","501"],"platforms":[{"latitude":50055980,"longitude":14365309,"transport":"Bus","lines":["130","149","501"]},{"latitude":50055751,"longitude":14365070,"transport":"Bus","lines":["130","149","501"]}]},{"name":"Vinice","lines":["7","11","55"],"platforms":[{"latitude":50076778,"longitude":14490492,"transport":"Tram","lines":["7","11","55"]}]},{"name":"Vinohradská tržnice","lines":["11"],"platforms":[{"latitude":50077041,"longitude":14442925,"transport":"Tram","lines":["11"]},{"latitude":50077018,"longitude":14441801,"transport":"Tram","lines":["11"]}]},{"name":"Vinohradská vodárna","lines":["10","16","51"],"platforms":[{"latitude":50075458,"longitude":14449399,"transport":"Tram","lines":["10","16","51"]},{"latitude":50075321,"longitude":14450211,"transport":"Tram","lines":["10","16","51"]}]},{"name":"Vinohradské hřbitovy","lines":["11","19","26","51"],"platforms":[{"latitude":50077770,"longitude":14480304,"transport":"Tram","lines":["11","19","26","51"]},{"latitude":50077560,"longitude":14481121,"transport":"Tram","lines":["11","19","26","51"]}]},{"name":"Vinopalnická","lines":["102"],"platforms":[{"latitude":50120006,"longitude":14470296,"transport":"Bus","lines":["102"]}]},{"name":"Vinoř","lines":["259","375","378","513","554","603"],"platforms":[{"latitude":50151981,"longitude":14591286,"transport":"Bus","lines":["259","378","513"]},{"latitude":50151878,"longitude":14591400,"transport":"Bus","lines":["259","375","378","513","603"]}]},{"name":"Vinořský hřbitov","lines":["259","302","375","378","513","554","603"],"platforms":[{"latitude":50145122,"longitude":14578371,"transport":"Bus","lines":["302"]},{"latitude":50144363,"longitude":14579163,"transport":"Bus","lines":["302"]},{"latitude":50144943,"longitude":14580558,"transport":"Bus","lines":["259","375","378","513","603"]},{"latitude":50145378,"longitude":14581422,"transport":"Bus","lines":["259","375","378","513","603"]}]},{"name":"Višňová","lines":["121","203"],"platforms":[{"latitude":50031303,"longitude":14447827,"transport":"Bus","lines":["121","203"]},{"latitude":50031196,"longitude":14447716,"transport":"Bus","lines":["121","203"]}]},{"name":"Vítězné náměstí","lines":["2","8","20","26","36","51","502","515","604","615"],"platforms":[{"latitude":50100051,"longitude":14395618,"transport":"Tram","lines":["2","8","20","26","36","51"]},{"latitude":50099628,"longitude":14395449,"transport":"Tram","lines":["2","8","20","26","36","51"]},{"latitude":50099319,"longitude":14395686,"transport":"Bus","lines":["502","515","604"]},{"latitude":50099063,"longitude":14395548,"transport":"Bus","lines":["502","515","604"]}]},{"name":"Vlastibořská","lines":["220"],"platforms":[{"latitude":50120189,"longitude":14598235,"transport":"Bus","lines":["220"]}]},{"name":"Vlastina","lines":["108","179","206","225","510"],"platforms":[{"latitude":50091236,"longitude":14316431,"transport":"Bus","lines":["108","179","206","225","510"]},{"latitude":50091068,"longitude":14316083,"transport":"Bus","lines":["108","179","206","225","510"]}]},{"name":"Vlašimská","lines":["136","175"],"platforms":[{"latitude":50074314,"longitude":14466477,"transport":"Bus","lines":["136","175"]},{"latitude":50074432,"longitude":14463838,"transport":"Bus","lines":["136","175"]}]},{"name":"Vlnitá","lines":["192"],"platforms":[{"latitude":50035449,"longitude":14421943,"transport":"Bus","lines":["192"]},{"latitude":50034774,"longitude":14420602,"transport":"Bus","lines":["192"]}]},{"name":"Vltavská","lines":["1","3","5","25","156","505","511","C"],"platforms":[{"latitude":50099327,"longitude":14438670,"transport":"Subway entry","lines":["C"]},{"latitude":50099094,"longitude":14438444,"transport":"Subway entry","lines":["C"]},{"latitude":50099040,"longitude":14438632,"transport":"Tram","lines":["1","3","5","25"]},{"latitude":50098308,"longitude":14438698,"transport":"Bus","lines":["505","511"]},{"latitude":50098106,"longitude":14438653,"transport":"Bus","lines":["505","511"]},{"latitude":50099304,"longitude":14438270,"transport":"Tram","lines":["1","3","5","25"]}]},{"name":"Vodičkova","lines":["3","9","14","24","51","52","54","55","56","58","91"],"platforms":[{"latitude":50079956,"longitude":14423307,"transport":"Tram","lines":["3","9","14","24","51","52","54","55","56","58"]},{"latitude":50079631,"longitude":14422681,"transport":"Tram","lines":["3","9","14","24","51","52","54","55","56","58"]}]},{"name":"Vojenská nemocnice","lines":["1","2","18","56","216"],"platforms":[{"latitude":50091865,"longitude":14359914,"transport":"Tram","lines":["1","2","18","56"]},{"latitude":50091724,"longitude":14360403,"transport":"Tram","lines":["1","2","18","56"]}]},{"name":"Vojická","lines":["221","269","273","303","304","344","353","354","512"],"platforms":[{"latitude":50114032,"longitude":14604373,"transport":"Bus","lines":["221","269","273","303","304","344","353","512"]},{"latitude":50113769,"longitude":14603464,"transport":"Bus","lines":["221","269","273","303","304","344","353","512"]}]},{"name":"Volha","lines":["177","197","511"],"platforms":[{"latitude":50021633,"longitude":14492774,"transport":"Bus","lines":["177","197","511"]},{"latitude":50021469,"longitude":14493223,"transport":"Bus","lines":["177","197","511"]},{"latitude":50021511,"longitude":14492893,"transport":"Bus","lines":["197"]}]},{"name":"Vosmíkových","lines":["24","25","X24","X55"],"platforms":[{"latitude":50114410,"longitude":14473620,"transport":"Tram","lines":["10","24","25","55"]},{"latitude":50114307,"longitude":14472290,"transport":"Tram","lines":["10","24","25","55"]}]},{"name":"Votuzská","lines":["221","303","304","344","353","354","562"],"platforms":[{"latitude":50116947,"longitude":14621862,"transport":"Bus","lines":["221","303","304","344","353"]},{"latitude":50116817,"longitude":14621802,"transport":"Bus","lines":["221","303","304","344","353"]}]},{"name":"Vozovna Kobylisy","lines":["14","136","162","169","183","370","371","372","373","374","551","608","X55"],"platforms":[{"latitude":50132091,"longitude":14453650,"transport":"Tram","lines":["14","25"]},{"latitude":50132968,"longitude":14453716,"transport":"Tram","lines":["25"]},{"latitude":50132781,"longitude":14453585,"transport":"Tram","lines":["14","55"]},{"latitude":50133197,"longitude":14453181,"transport":"Bus","lines":["370","371","372","373","374"]},{"latitude":50132732,"longitude":14453136,"transport":"Bus","lines":["162","169","183"]},{"latitude":50132434,"longitude":14453630,"transport":"Tram","lines":["14","25","55"]},{"latitude":50132682,"longitude":14454163,"transport":"Tram","lines":["14","25","55"]},{"latitude":50133003,"longitude":14452841,"transport":"Bus","lines":["136","162","169","183","370","371","372","373","374"]},{"latitude":50133270,"longitude":14455041,"transport":"Bus","lines":["136"]},{"latitude":50133010,"longitude":14455335,"transport":"Bus","lines":["136"]}]},{"name":"Vozovna Motol","lines":["9","10","16","58","59"],"platforms":[{"latitude":50067943,"longitude":14340534,"transport":"Tram","lines":["9","10","16","58","59"]},{"latitude":50067771,"longitude":14341362,"transport":"Tram","lines":["9","10","16","58","59"]}]},{"name":"Vozovna Pankrác","lines":["18","53"],"platforms":[{"latitude":50056961,"longitude":14438043,"transport":"Tram","lines":["18","53"]},{"latitude":50056972,"longitude":14437047,"transport":"Tram","lines":["18","53"]}]},{"name":"Vozovna Strašnice","lines":["11","19","26","51"],"platforms":[{"latitude":50076858,"longitude":14488353,"transport":"Tram","lines":["11","19","26","51"]},{"latitude":50077098,"longitude":14487367,"transport":"Tram","lines":["11","19","26","51"]}]},{"name":"Vozovna Střešovice","lines":["1","2","18","56","91","143","149","174","180","216","217","502"],"platforms":[{"latitude":50093811,"longitude":14388280,"transport":"Bus","lines":["216"]},{"latitude":50093967,"longitude":14389613,"transport":"Bus","lines":["108","143","149","174","180","217","502"]},{"latitude":50094009,"longitude":14390068,"transport":"Bus","lines":["108","143","149","174","180","217","502"]},{"latitude":50093692,"longitude":14389062,"transport":"Tram","lines":["1","2","18","56"]},{"latitude":50094249,"longitude":14390632,"transport":"Tram","lines":["1","2","18","56"]},{"latitude":50093784,"longitude":14387988,"transport":"Bus","lines":["216"]}]},{"name":"Vozovna Vokovice","lines":["20","26","36","51"],"platforms":[{"latitude":50093200,"longitude":14331339,"transport":"Tram","lines":["20","26","36","51"]},{"latitude":50092971,"longitude":14330747,"transport":"Tram","lines":["20","26","36","51"]}]},{"name":"Vratislavova","lines":["552"],"platforms":[]},{"name":"Vrážská","lines":["165","244"],"platforms":[{"latitude":49989894,"longitude":14369723,"transport":"Bus","lines":["165","172","244"]},{"latitude":49990371,"longitude":14370532,"transport":"Bus","lines":["165","172","244"]}]},{"name":"Vrbova","lines":["196","197","198","501"],"platforms":[{"latitude":50031837,"longitude":14425745,"transport":"Bus","lines":["196","197","198","501"]}]},{"name":"Vršovické náměstí","lines":["4","22","57","59"],"platforms":[{"latitude":50069187,"longitude":14454238,"transport":"Tram","lines":["4","22","57","59"]}]},{"name":"Vršovický hřbitov","lines":["101"],"platforms":[{"latitude":50062980,"longitude":14467006,"transport":"Bus","lines":["101"]},{"latitude":50063617,"longitude":14466455,"transport":"Bus","lines":["101"]}]},{"name":"VÚ Běchovice","lines":["109","261","269"],"platforms":[{"latitude":50089309,"longitude":14612395,"transport":"Bus","lines":["109","261","269"]},{"latitude":50089019,"longitude":14612400,"transport":"Bus","lines":["109","261","269"]}]},{"name":"Výhledské náměstí","lines":["147","359"],"platforms":[{"latitude":50135055,"longitude":14373290,"transport":"Bus","lines":["147","359"]},{"latitude":50134918,"longitude":14373266,"transport":"Bus","lines":["147","359"]}]},{"name":"Výhledy","lines":["147","359"],"platforms":[{"latitude":50137172,"longitude":14368678,"transport":"Bus","lines":["147","359"]}]},{"name":"Vychovatelna","lines":["102","186","295","505","511","X24","X55"],"platforms":[{"latitude":50119052,"longitude":14464406,"transport":"Tram","lines":["10","24","25","55"]},{"latitude":50119316,"longitude":14463631,"transport":"Tram","lines":["10","24","25","55"]},{"latitude":50118698,"longitude":14464125,"transport":"Bus","lines":["505"]},{"latitude":50117790,"longitude":14464754,"transport":"Bus","lines":["102","186","511"]},{"latitude":50117603,"longitude":14463827,"transport":"Bus","lines":["102","186","295","505"]}]},{"name":"Vypich","lines":["22","25","57","174","179","180","191","502","510","560"],"platforms":[{"latitude":50080413,"longitude":14344134,"transport":"Bus","lines":["179","184","510"]},{"latitude":50080234,"longitude":14344227,"transport":"Bus","lines":["108","179","184","191","225","510"]},{"latitude":50079818,"longitude":14347700,"transport":"Tram","lines":["22","25","57"]},{"latitude":50079765,"longitude":14346615,"transport":"Tram","lines":["22","25","57"]},{"latitude":50079681,"longitude":14346363,"transport":"Bus","lines":["108","174","180","191","502","510","I2"]},{"latitude":50079402,"longitude":14346167,"transport":"Bus","lines":["108","174","180","191","502","510","I2"]}]},{"name":"Vysočanská","lines":["15","55","136","151","158","177","183","195","375","B","*E"],"platforms":[{"latitude":50111568,"longitude":14502776,"transport":"Tram","lines":["15","55"]},{"latitude":50110378,"longitude":14501843,"transport":"Subway entry","lines":["B"]},{"latitude":50110370,"longitude":14502422,"transport":"Subway entry","lines":["B"]},{"latitude":50110916,"longitude":14502324,"transport":"Bus","lines":["136","177","183","195"]},{"latitude":50110176,"longitude":14501922,"transport":"Bus","lines":["151","158","375"]},{"latitude":50110305,"longitude":14502184,"transport":"Bus","lines":["136","177","183"]},{"latitude":50110595,"longitude":14502363,"transport":"Bus","lines":["151","158","195","375"]},{"latitude":50109947,"longitude":14499284,"transport":"Subway entry","lines":["B"]}]},{"name":"Vysokovská","lines":["223","296"],"platforms":[{"latitude":50109073,"longitude":14602759,"transport":"Bus","lines":["223","296"]}]},{"name":"Výstaviště","lines":["5","12","14","15","17","53","54","91"],"platforms":[{"latitude":50104343,"longitude":14430247,"transport":"Tram","lines":["5","17"]},{"latitude":50104080,"longitude":14430296,"transport":"Tram","lines":["5","17"]},{"latitude":50104587,"longitude":14432201,"transport":"Tram","lines":["5","12","14","15","17","53","54"]},{"latitude":50104869,"longitude":14432867,"transport":"Tram","lines":["5","12","14","15","17","53","54"]}]},{"name":"Výstaviště Letňany","lines":["110","140","158","186","195","269","295","511","513","603"],"platforms":[{"latitude":50128616,"longitude":14511651,"transport":"Bus","lines":["110","140","158","186","195","269","295","351","365","511","513","603"]},{"latitude":50128410,"longitude":14512081,"transport":"Bus","lines":["110","140","158","186","195","269","295","351","365","511","513","603"]}]},{"name":"Vyšehrad","lines":["504","505","510","C"],"platforms":[{"latitude":50059280,"longitude":14430540,"transport":"Bus","lines":["504","505","510"]},{"latitude":50059005,"longitude":14430836,"transport":"Bus","lines":["504","505","510"]},{"latitude":50063095,"longitude":14430827,"transport":"Subway entry","lines":["C"]},{"latitude":50063098,"longitude":14430150,"transport":"Subway entry","lines":["C"]}]},{"name":"Výtoň","lines":["3","7","17","21","52","P5"],"platforms":[{"latitude":50068115,"longitude":14415022,"transport":"Tram","lines":["3","7","17","21","52"]},{"latitude":50067798,"longitude":14414875,"transport":"Tram","lines":["3","7","17","21","52"]}]}]}