{"stops":[{"name":"Madlina","lines":["151","186","295","511"],"platforms":[{"latitude":50120563,"longitude":14484754,"transport":"Bus","lines":["151","186","295","511"]},{"latitude":50120292,"longitude":14484430,"transport":"Bus","lines":["151","186","295","511"]}]},{"name":"Macharovo náměstí","lines":["216"],"platforms":[{"latitude":50094158,"longitude":14381405,"transport":"Bus","lines":["216"]}]},{"name":"Malá Chuchle","lines":["129","241","243","244","314","318","507"],"platforms":[{"latitude":50025344,"longitude":14395045,"transport":"Bus","lines":["129","172","241","243","244","314","318","507"]},{"latitude":50024856,"longitude":14394529,"transport":"Bus","lines":["129","172","241","243","244","314","318","507"]}]},{"name":"Malá Ohrada","lines":["214","225","235","508","566"],"platforms":[{"latitude":50044612,"longitude":14338707,"transport":"Bus","lines":["142","211","225","235","256","508"]},{"latitude":50043594,"longitude":14337032,"transport":"Bus","lines":["142","211","225","235","256","508"]}]},{"name":"Malešická","lines":["124","133","297","509"],"platforms":[{"latitude":50086868,"longitude":14481948,"transport":"Bus","lines":["124","133","297","509"]},{"latitude":50086509,"longitude":14481916,"transport":"Bus","lines":["124","133","297","509"]}]},{"name":"Malešická stráň","lines":["297"],"platforms":[{"latitude":50085098,"longitude":14503184,"transport":"Bus","lines":["297"]},{"latitude":50085422,"longitude":14501766,"transport":"Bus","lines":["297"]}]},{"name":"Malešická továrna","lines":["7","55","122","163","263","265","266","364","366"],"platforms":[{"latitude":50077308,"longitude":14525335,"transport":"Bus","lines":["122","163","263","265","266","364","366"]},{"latitude":50077331,"longitude":14525167,"transport":"Tram","lines":["7","55"]},{"latitude":50077083,"longitude":14525965,"transport":"Tram","lines":["7","55"]},{"latitude":50077079,"longitude":14526091,"transport":"Bus","lines":["122","163","263","265","266","364","366"]}]},{"name":"Malešické náměstí","lines":["177","195","297"],"platforms":[{"latitude":50084793,"longitude":14510952,"transport":"Bus","lines":["177","195","297"]},{"latitude":50084663,"longitude":14510457,"transport":"Bus","lines":["297"]}]},{"name":"Malostranská","lines":["12","18","20","22","57","91","A"],"platforms":[{"latitude":50090793,"longitude":14410088,"transport":"Tram","lines":["12","18","20","22","57"]},{"latitude":50091484,"longitude":14410334,"transport":"Tram","lines":["12","51","56"]},{"latitude":50091968,"longitude":14409605,"transport":"Bus","lines":["I2"]},{"latitude":50091865,"longitude":14411063,"transport":"Bus","lines":["I2"]},{"latitude":50090297,"longitude":14410088,"transport":"Tram","lines":["12","18","20","22","51","56","57"]},{"latitude":50090957,"longitude":14409575,"transport":"Subway entry","lines":["A"]}]},{"name":"Malostranské náměstí","lines":["12","20","22","57","91","292"],"platforms":[{"latitude":50088283,"longitude":14404488,"transport":"Tram","lines":["12","20","22","57"]},{"latitude":50087879,"longitude":14404637,"transport":"Bus","lines":["292"]},{"latitude":50087993,"longitude":14404273,"transport":"Tram","lines":["12","20","22","57"]}]},{"name":"Malovanka","lines":["22","25","57","143","149","217"],"platforms":[{"latitude":50085361,"longitude":14383238,"transport":"Bus","lines":["143","149","217"]},{"latitude":50085594,"longitude":14381833,"transport":"Tram","lines":["22","25","57"]},{"latitude":50085609,"longitude":14382693,"transport":"Tram","lines":["22","25","57"]},{"latitude":50085559,"longitude":14383280,"transport":"Bus","lines":["143","149","217"]},{"latitude":50085430,"longitude":14380992,"transport":"Bus","lines":["108","174","180","502"]},{"latitude":50085521,"longitude":14382109,"transport":"Bus","lines":["108","174","180","502"]}]},{"name":"Malvazinky","lines":["137","501"],"platforms":[{"latitude":50064998,"longitude":14388588,"transport":"Bus","lines":["137","501"]},{"latitude":50064903,"longitude":14388136,"transport":"Bus","lines":["137","501"]}]},{"name":"Malý Břevnov","lines":["22","57","347","560"],"platforms":[{"latitude":50076313,"longitude":14333424,"transport":"Tram","lines":["22","57"]},{"latitude":50076442,"longitude":14334382,"transport":"Tram","lines":["22","57"]},{"latitude":50076286,"longitude":14332799,"transport":"Bus","lines":["108","347"]},{"latitude":50076011,"longitude":14332488,"transport":"Bus","lines":["108","347"]}]},{"name":"Maniny","lines":["1","3","12","15","25","54","156"],"platforms":[{"latitude":50103237,"longitude":14453861,"transport":"Tram","lines":["1","3","10","12","15","25","54"]},{"latitude":50103355,"longitude":14452794,"transport":"Tram","lines":["1","3","10","12","25","54"]}]},{"name":"Marjánka","lines":["22","25","57"],"platforms":[{"latitude":50084514,"longitude":14375844,"transport":"Tram","lines":["22","25","57"]},{"latitude":50084480,"longitude":14374891,"transport":"Tram","lines":["22","25","57"]}]},{"name":"Masarykovo nádraží","lines":["3","5","14","24","26","51","52","54","56","91","504","505","509","511"],"platforms":[{"latitude":50088142,"longitude":14432555,"transport":"Bus","lines":["504","505","509","511","AE","I1"]},{"latitude":50087535,"longitude":14432490,"transport":"Bus","lines":["504","505","509","511","AE","I1"]},{"latitude":50088020,"longitude":14432589,"transport":"Tram","lines":["3","5","14","24","26","51","52","54","56"]},{"latitude":50087635,"longitude":14432443,"transport":"Tram","lines":["3","5","14","24","26","51","52","54","56"]}]},{"name":"Maškův mlýn","lines":["256"],"platforms":[{"latitude":49998985,"longitude":14318163,"transport":"Bus","lines":["256"]},{"latitude":49998901,"longitude":14318374,"transport":"Bus","lines":["256"]}]},{"name":"Měděnecká","lines":["162"],"platforms":[{"latitude":50149635,"longitude":14448867,"transport":"Bus","lines":["162"]},{"latitude":50149757,"longitude":14448459,"transport":"Bus","lines":["162"]}]},{"name":"Měchenická","lines":["118"],"platforms":[{"latitude":50050148,"longitude":14488197,"transport":"Bus","lines":["118"]},{"latitude":50049880,"longitude":14488895,"transport":"Bus","lines":["118"]}]},{"name":"Městský archiv","lines":["115"],"platforms":[{"latitude":50041057,"longitude":14495314,"transport":"Bus","lines":["115"]}]},{"name":"Metodějova","lines":["122","135","213","506","511","605","609"],"platforms":[{"latitude":50026126,"longitude":14520786,"transport":"Bus","lines":["122","135","213","506","511","605","609"]},{"latitude":50026065,"longitude":14521183,"transport":"Bus","lines":["122","135","213","506","511","605","609"]}]},{"name":"Mezi Hřbitovy","lines":["10","16","19","26","58","124"],"platforms":[{"latitude":50082210,"longitude":14471716,"transport":"Tram","lines":["10","16","19","26","58"]},{"latitude":50082771,"longitude":14472484,"transport":"Bus","lines":["124"]},{"latitude":50082637,"longitude":14472227,"transport":"Bus","lines":["124"]},{"latitude":50081851,"longitude":14471629,"transport":"Tram","lines":["10","16","19","26","58"]}]},{"name":"Michelangelova","lines":["111","271","296","329","509"],"platforms":[{"latitude":50070358,"longitude":14509430,"transport":"Bus","lines":["111","271","296","329","509"]},{"latitude":50070148,"longitude":14509811,"transport":"Bus","lines":["111","271","296","329","509"]}]},{"name":"Michelská","lines":["11","56","106","124","139","150","182","188"],"platforms":[{"latitude":50055015,"longitude":14454252,"transport":"Tram","lines":["11","56"]},{"latitude":50055068,"longitude":14453779,"transport":"Tram","lines":["11","56"]},{"latitude":50054771,"longitude":14453167,"transport":"Bus","lines":["106","124","139","150","182"]},{"latitude":50054836,"longitude":14452670,"transport":"Bus","lines":["106","124","139","182"]},{"latitude":50055072,"longitude":14453890,"transport":"Bus","lines":["150","188"]},{"latitude":50055057,"longitude":14454355,"transport":"Bus","lines":["188"]}]},{"name":"Michelský les","lines":["106","114","170","182","193","504","510"],"platforms":[{"latitude":50035865,"longitude":14455954,"transport":"Bus","lines":["106","114","170","182","193","504","510"]},{"latitude":50035270,"longitude":14456043,"transport":"Bus","lines":["106","114","170","182","193","504","510"]}]},{"name":"Mikulova","lines":["125","165","293"],"platforms":[{"latitude":50031990,"longitude":14514625,"transport":"Bus","lines":["125","165","293"]},{"latitude":50031917,"longitude":14514780,"transport":"Bus","lines":["125","165","293"]}]},{"name":"Milevská","lines":["148","188"],"platforms":[]},{"name":"Mirovická","lines":["162","169","183"],"platforms":[{"latitude":50131416,"longitude":14452774,"transport":"Bus","lines":["162","169","183"]},{"latitude":50130352,"longitude":14452131,"transport":"Bus","lines":["162","169","183"]}]},{"name":"Miškovice","lines":["158","202","365","*T"],"platforms":[{"latitude":50156032,"longitude":14541372,"transport":"Bus","lines":["158","202","365"]},{"latitude":50156047,"longitude":14541776,"transport":"Bus","lines":["158"]},{"latitude":50155689,"longitude":14541831,"transport":"Bus","lines":["202"]}]},{"name":"Mladějovská","lines":["259","375","378"],"platforms":[{"latitude":50132762,"longitude":14560608,"transport":"Bus","lines":["259","375","378"]},{"latitude":50132553,"longitude":14560482,"transport":"Bus","lines":["259","375","378"]}]},{"name":"Mládí","lines":["130","174","502"],"platforms":[{"latitude":50049999,"longitude":14321606,"transport":"Bus","lines":["130","174","502"]},{"latitude":50050109,"longitude":14323208,"transport":"Bus","lines":["130","174","502"]}]},{"name":"Modrá škola","lines":["125","154","165","170","203","293","505","605"],"platforms":[{"latitude":50031764,"longitude":14523409,"transport":"Bus","lines":["125","154","165","170","203","293","505","605"]},{"latitude":50030395,"longitude":14524526,"transport":"Bus","lines":["125","154","165","170","203","293","505","605"]}]},{"name":"Modřanská rokle","lines":["3","17","52","117","165"],"platforms":[{"latitude":50006401,"longitude":14428942,"transport":"Tram","lines":["3","17","52"]},{"latitude":50006507,"longitude":14429287,"transport":"Bus","lines":["117","165"]},{"latitude":50006458,"longitude":14428451,"transport":"Tram","lines":["3","17","52"]},{"latitude":50006706,"longitude":14428919,"transport":"Bus","lines":["117","165"]}]},{"name":"Modřanská škola","lines":["3","17","52","173"],"platforms":[{"latitude":50009838,"longitude":14402947,"transport":"Bus","lines":["173"]},{"latitude":50009178,"longitude":14402998,"transport":"Tram","lines":["3","17","52"]},{"latitude":50008686,"longitude":14403474,"transport":"Bus","lines":["173"]},{"latitude":50008453,"longitude":14403050,"transport":"Tram","lines":["3","17","52"]}]},{"name":"Mokrá","lines":["170","203","505"],"platforms":[{"latitude":50033580,"longitude":14504862,"transport":"Bus","lines":["170","203","505"]},{"latitude":50033329,"longitude":14503190,"transport":"Bus","lines":["170","203","505"]}]},{"name":"Mokřanská","lines":["111","271","329","509"],"platforms":[{"latitude":50063762,"longitude":14526550,"transport":"Bus","lines":["111","271","329","509"]},{"latitude":50063140,"longitude":14526816,"transport":"Bus","lines":["111","271","329","509"]}]},{"name":"Moráň","lines":["3","4","10","16","18","21","24","52","53","54","55"],"platforms":[{"latitude":50074035,"longitude":14418571,"transport":"Tram","lines":["3","4","10","16","18","21","24","52","53","54","55"]}]},{"name":"Moravanská","lines":["302"],"platforms":[{"latitude":50148452,"longitude":14578487,"transport":"Bus","lines":["302"]},{"latitude":50147792,"longitude":14578501,"transport":"Bus","lines":["302"]}]},{"name":"Morseova","lines":["154"],"platforms":[{"latitude":50035079,"longitude":14558711,"transport":"Bus","lines":["154"]},{"latitude":50035045,"longitude":14558926,"transport":"Bus","lines":["154"]}]},{"name":"Most Závodu míru","lines":["165","314","338","361","390"],"platforms":[{"latitude":49972923,"longitude":14394929,"transport":"Bus","lines":["165","314"]},{"latitude":49972782,"longitude":14395046,"transport":"Bus","lines":["165","314"]}]},{"name":"Motol","lines":["9","10","16","58","59","168","174","179","180","347","502"],"platforms":[{"latitude":50068717,"longitude":14335374,"transport":"Bus","lines":["174","179","180","184","347","502"]},{"latitude":50068786,"longitude":14335204,"transport":"Bus","lines":["174","179","180","184","347","502"]},{"latitude":50067794,"longitude":14336000,"transport":"Tram","lines":["9","10","16","58","59"]},{"latitude":50067619,"longitude":14336840,"transport":"Tram","lines":["9","10","16","58","59"]}]},{"name":"Mototechna","lines":["164"],"platforms":[{"latitude":50054172,"longitude":14317119,"transport":"Bus","lines":["164","219"]},{"latitude":50054126,"longitude":14315394,"transport":"Bus","lines":["164","219"]}]},{"name":"Murmanská","lines":["175"],"platforms":[{"latitude":50073017,"longitude":14480927,"transport":"Bus","lines":["175"]},{"latitude":50073772,"longitude":14478398,"transport":"Bus","lines":["175"]}]},{"name":"Můstek","lines":["A"],"platforms":[]},{"name":"Můstek","lines":["B"],"platforms":[]},{"name":"Muzeum","lines":["11","504","505","511"],"platforms":[{"latitude":50079025,"longitude":14432696,"transport":"Tram","lines":["11"]},{"latitude":50078876,"longitude":14432582,"transport":"Tram","lines":["11"]},{"latitude":50080070,"longitude":14431007,"transport":"Bus","lines":["504","505","511"]},{"latitude":50079757,"longitude":14429701,"transport":"Subway entry","lines":["C"]},{"latitude":50079849,"longitude":14430240,"transport":"Subway entry","lines":["C"]},{"latitude":50079383,"longitude":14429513,"transport":"Subway entry","lines":["C"]},{"latitude":50078716,"longitude":14430035,"transport":"Subway entry","lines":["C"]},{"latitude":50079402,"longitude":14431113,"transport":"Subway entry","lines":["C"]}]},{"name":"Muzeum","lines":["A"],"platforms":[]},{"name":"Muzeum","lines":["C"],"platforms":[]},{"name":"Myslíkova","lines":["14"],"platforms":[{"latitude":50077964,"longitude":14417985,"transport":"Tram","lines":["14"]},{"latitude":50078151,"longitude":14418845,"transport":"Tram","lines":["14"]}]},{"name":"Myšlínská","lines":["111","271","329","509"],"platforms":[{"latitude":50061790,"longitude":14533650,"transport":"Bus","lines":["111","329"]},{"latitude":50062202,"longitude":14534444,"transport":"Bus","lines":["271","329"]},{"latitude":50062290,"longitude":14534606,"transport":"Bus","lines":["111","271","329","509"]}]}]}